README.txt
setup.cfg
setup.py
collective/__init__.py
collective.fancybox.egg-info/PKG-INFO
collective.fancybox.egg-info/SOURCES.txt
collective.fancybox.egg-info/dependency_links.txt
collective.fancybox.egg-info/entry_points.txt
collective.fancybox.egg-info/namespace_packages.txt
collective.fancybox.egg-info/not-zip-safe
collective.fancybox.egg-info/requires.txt
collective.fancybox.egg-info/top_level.txt
collective/fancybox/__init__.py
collective/fancybox/configure.zcml
collective/fancybox/dtmlresource.py
collective/fancybox/fancybox/UPDATING.txt
collective/fancybox/fancybox/blank.gif
collective/fancybox/fancybox/fancy_close.png
collective/fancybox/fancybox/fancy_loading.png
collective/fancybox/fancybox/fancy_nav_left.png
collective/fancybox/fancybox/fancy_nav_right.png
collective/fancybox/fancybox/fancy_shadow_e.png
collective/fancybox/fancybox/fancy_shadow_n.png
collective/fancybox/fancybox/fancy_shadow_ne.png
collective/fancybox/fancybox/fancy_shadow_nw.png
collective/fancybox/fancybox/fancy_shadow_s.png
collective/fancybox/fancybox/fancy_shadow_se.png
collective/fancybox/fancybox/fancy_shadow_sw.png
collective/fancybox/fancybox/fancy_shadow_w.png
collective/fancybox/fancybox/fancy_title_left.png
collective/fancybox/fancybox/fancy_title_main.png
collective/fancybox/fancybox/fancy_title_over.png
collective/fancybox/fancybox/fancy_title_right.png
collective/fancybox/fancybox/fancybox-x.png
collective/fancybox/fancybox/fancybox-y.png
collective/fancybox/fancybox/fancybox.png
collective/fancybox/fancybox/jquery.easing-1.3.pack.js
collective/fancybox/fancybox/jquery.fancybox.css.dtml
collective/fancybox/fancybox/jquery.fancybox.js
collective/fancybox/fancybox/jquery.fancybox.pack.js
collective/fancybox/fancybox/jquery.mousewheel-3.0.4.pack.js
collective/fancybox/profiles/default/cssregistry.xml
collective/fancybox/profiles/default/jsregistry.xml
collective/fancybox/profiles/default/metadata.xml
docs/HISTORY.txt
docs/INSTALL.txt
docs/LICENSE.GPL
docs/LICENSE.txt