Metadata-Version: 1.0
Name: collective.fancybox
Version: 0.5
Summary: Fancybox libraries for Plone
Home-page: http://pypi.python.org/pypi/collective.fancybox
Author: Radim Novotny
Author-email: novotny.radim@gmail.com
License: GPL
Keywords: fancybox plone jquery
Platform: UNKNOWN
Classifier: Framework :: Plone
Classifier: Programming Language :: Python
Classifier: Topic :: Software Development :: Libraries :: Python Modules
